americanas_scraper/__init__.py
americanas_scraper-0.0.2.data/scripts/americanas
americanas_scraper-0.0.2.dist-info/LICENSE
americanas_scraper-0.0.2.dist-info/METADATA
americanas_scraper-0.0.2.dist-info/WHEEL
americanas_scraper-0.0.2.dist-info/top_level.txt
americanas_scraper-0.0.2.dist-info/RECORD
