Metadata-Version: 2.1
Name: americanas-scraper
Version: 0.0.2
Summary: Americanas crawler and scraper using beautifulsoup4
Home-page: https://github.com/GeovRodri/americanas-scraper
Author: Geovany Rodrigues
Author-email: geovanyscv@gmail.com
License: UNKNOWN
Platform: UNKNOWN
Classifier: Development Status :: 5 - Production/Stable
Classifier: Intended Audience :: Developers
Classifier: License :: OSI Approved :: BSD License
Classifier: Environment :: Console
Classifier: Programming Language :: Python
Classifier: Topic :: Software Development :: Libraries :: Python Modules
Requires: beautifulsoup4
Provides: americanas_scraper
Requires-Dist: beautifulsoup4
